nonrepeat.py
nonrepeat-0.1.3.dist-info/WHEEL
nonrepeat-0.1.3.dist-info/METADATA
nonrepeat-0.1.3.dist-info/RECORD
