Metadata-Version: 2.1
Name: nonrepeat
Version: 0.1.3
Summary: Generate non-repeat filenames, ids and strings
Home-page: UNKNOWN
License: MIT
Author: Pacharapol Withayasakpunt
Author-email: patarapolw@gmail.com
Classifier: License :: OSI Approved :: MIT License
Classifier: Programming Language :: Python :: 2
Classifier: Programming Language :: Python :: 2.7
Classifier: Programming Language :: Python :: 3
Classifier: Programming Language :: Python :: 3.4
Classifier: Programming Language :: Python :: 3.5
Classifier: Programming Language :: Python :: 3.6
Classifier: Programming Language :: Python :: 3.7
